{
  "search": "BIBS",
  "products": [
    {
      "handle": "bibs-smoczek-2-pak-latex-kosc-sloniowa-szalwia",
      "title": "BIBS Smoczek 2 Pak Latex Kość Słoniowa /Szałwia",
      "vendor": "BIBS",
      "product_type": "Pacifier",
      "option_name": "Size",
      "option_values": [
        "1"
      ],
      "tags": [
        "BIBS",
        "Pacifier",
        "Ogólna"
      ],
      "files": {
        "https-b2b-aico2012-e-aico-com-pl-obrazki-bib000101-110241y-20-458-20x-20458-jpg": "https://b2b:aico2012@e.aico.com.pl/Obrazki/BIB000101_110241y%20(458%20x%20458).jpg"
      },
      "variants": [
        {
          "option_value": "1",
          "sku": "BIB000101",
          "barcode": "5713795110438",
          "price": "21.87",
          "detail_url": "https://e.aico.com.pl/ProduktySzczegoly.aspx?id_artykulu=Jud0dQ5W8EJThA3vbpLVSA",
          "source_code": "110241",
          "source_title": "BIBS 110241 SMOCZEK 2 PAK LATEX ROZMIAR 1 KOŚĆ SŁONIOWA /SZAŁWIA",
          "file_key": "https-b2b-aico2012-e-aico-com-pl-obrazki-bib000101-110241y-20-458-20x-20458-jpg",
          "source_sku": "BIB000101"
        }
      ]
    },
    {
      "handle": "bibs-smoczek-2-pak-latex-roz-wanilia-swiecacy",
      "title": "BIBS Smoczek 2 Pak Latex Róż/Wanilia Świecący",
      "vendor": "BIBS",
      "product_type": "Pacifier",
      "option_name": "Size",
      "option_values": [
        "1"
      ],
      "tags": [
        "BIBS",
        "Pacifier",
        "Ogólna"
      ],
      "files": {
        "https-b2b-aico2012-e-aico-com-pl-obrazki-bib000104-110243f-20-458-20x-20458-jpg": "https://b2b:aico2012@e.aico.com.pl/Obrazki/BIB000104_110243f%20(458%20x%20458).jpg"
      },
      "variants": [
        {
          "option_value": "1",
          "sku": "BIB000104",
          "barcode": "5713795210015",
          "price": "23.92",
          "detail_url": "https://e.aico.com.pl/ProduktySzczegoly.aspx?id_artykulu=16E9EafxeFAPWxMu5he7WQ",
          "source_code": "110243",
          "source_title": "BIBS 110243 SMOCZEK 2 PAK LATEX ROZMIAR 1 RÓŻ/WANILIA ŚWIECĄCY",
          "file_key": "https-b2b-aico2012-e-aico-com-pl-obrazki-bib000104-110243f-20-458-20x-20458-jpg",
          "source_sku": "BIB000104"
        }
      ]
    },
    {
      "handle": "bibs-smoczek-latex-baby-blue",
      "title": "BIBS Smoczek Latex Baby Blue",
      "vendor": "BIBS",
      "product_type": "Pacifier",
      "option_name": "Size",
      "option_values": [
        "1"
      ],
      "tags": [
        "BIBS",
        "Pacifier",
        "Ogólna"
      ],
      "files": {
        "https-b2b-aico2012-e-aico-com-pl-obrazki-bib000086-5713795262717-3-bibs-colour-1pack-rnd-ltx-s1-babyblue-2000x2000-20-600-20x-20600-jpg": "https://b2b:aico2012@e.aico.com.pl/Obrazki/BIB000086_5713795262717_3_BIBS_Colour_1pack_rnd_LTX_S1_BabyBlue_2000x2000%20(600%20x%20600).jpg"
      },
      "variants": [
        {
          "option_value": "1",
          "sku": "BIB000086",
          "barcode": "5713795262717",
          "price": "10.82",
          "detail_url": "https://e.aico.com.pl/ProduktySzczegoly.aspx?id_artykulu=ZpdXFHWBasccJAQyHj0Dog",
          "source_code": "1001000231",
          "source_title": "BIBS 1001000231 SMOCZEK LATEX ROZMIAR 1 BABY BLUE",
          "file_key": "https-b2b-aico2012-e-aico-com-pl-obrazki-bib000086-5713795262717-3-bibs-colour-1pack-rnd-ltx-s1-babyblue-2000x2000-20-600-20x-20600-jpg",
          "source_sku": "BIB000086"
        }
      ]
    },
    {
      "handle": "bibs-smoczek-latex-kosc-sloniowa",
      "title": "BIBS Smoczek Latex Kość Słoniowa",
      "vendor": "BIBS",
      "product_type": "Pacifier",
      "option_name": "Size",
      "option_values": [
        "1"
      ],
      "tags": [
        "BIBS",
        "Pacifier",
        "Ogólna"
      ],
      "files": {
        "https-b2b-aico2012-e-aico-com-pl-obrazki-bib000084-5713795262700-3-bibs-colour-pack-rnd-latex-s1-ivory-2000x2000-20-600-20x-20600-jpg": "https://b2b:aico2012@e.aico.com.pl/Obrazki/BIB000084_5713795262700_3_BIBS_COLOUR_PACK_Rnd_Latex_S1_Ivory_2000x2000%20(600%20x%20600).jpg"
      },
      "variants": [
        {
          "option_value": "1",
          "sku": "BIB000084",
          "barcode": "5713795262700",
          "price": "10.82",
          "detail_url": "https://e.aico.com.pl/ProduktySzczegoly.aspx?id_artykulu=Afvu93XNUIZiRm5Rj2DpaQ",
          "source_code": "1001000216",
          "source_title": "BIBS 1001000216 SMOCZEK LATEX ROZMIAR 1 KOŚĆ SŁONIOWA",
          "file_key": "https-b2b-aico2012-e-aico-com-pl-obrazki-bib000084-5713795262700-3-bibs-colour-pack-rnd-latex-s1-ivory-2000x2000-20-600-20x-20600-jpg",
          "source_sku": "BIB000084"
        }
      ]
    },
    {
      "handle": "bibs-smoczek-latex-szalwia",
      "title": "BIBS Smoczek Latex Szałwia",
      "vendor": "BIBS",
      "product_type": "Pacifier",
      "option_name": "Size",
      "option_values": [
        "1"
      ],
      "tags": [
        "BIBS",
        "Pacifier",
        "Ogólna"
      ],
      "files": {
        "https-b2b-aico2012-e-aico-com-pl-obrazki-bib000083-100250-20-600-20x-20600-jpg": "https://b2b:aico2012@e.aico.com.pl/Obrazki/BIB000083_100250%20(600%20x%20600).jpg"
      },
      "variants": [
        {
          "option_value": "1",
          "sku": "BIB000083",
          "barcode": "5713795262748",
          "price": "10.82",
          "detail_url": "https://e.aico.com.pl/ProduktySzczegoly.aspx?id_artykulu=bmfCfjfzREPALy7Xp9pXqQ",
          "source_code": "1001000250",
          "source_title": "BIBS 1001000250 SMOCZEK LATEX ROZMIAR 1 SZAŁWIA",
          "file_key": "https-b2b-aico2012-e-aico-com-pl-obrazki-bib000083-100250-20-600-20x-20600-jpg",
          "source_sku": "BIB000083"
        }
      ]
    },
    {
      "handle": "bibs-smoczek-latex-wanilia",
      "title": "BIBS Smoczek Latex Wanilia",
      "vendor": "BIBS",
      "product_type": "Pacifier",
      "option_name": "Size",
      "option_values": [
        "1"
      ],
      "tags": [
        "BIBS",
        "Pacifier",
        "Ogólna"
      ],
      "files": {
        "https-b2b-aico2012-e-aico-com-pl-obrazki-bib000081-5713795262731-2-bibs-colour-vanilla-2000x2000-20-600-20x-20600-jpg": "https://b2b:aico2012@e.aico.com.pl/Obrazki/BIB000081_5713795262731_2_BIBS_COLOUR_Vanilla_2000x2000%20(600%20x%20600).jpg"
      },
      "variants": [
        {
          "option_value": "1",
          "sku": "BIB000081",
          "barcode": "5713795262731",
          "price": "10.82",
          "detail_url": "https://e.aico.com.pl/ProduktySzczegoly.aspx?id_artykulu=nUNXcfJfiipbEtmjw2uEUw",
          "source_code": "1001000245",
          "source_title": "BIBS 1001000245 SMOCZEK LATEX ROZMIAR 1 WANILIA",
          "file_key": "https-b2b-aico2012-e-aico-com-pl-obrazki-bib000081-5713795262731-2-bibs-colour-vanilla-2000x2000-20-600-20x-20600-jpg",
          "source_sku": "BIB000081"
        }
      ]
    },
    {
      "handle": "bibs-smoczek-liberty-pacifier-kolor-2-pak-latex-szalwia",
      "title": "BIBS Smoczek Liberty Pacifier Kolor 2 Pak Latex Szałwia",
      "vendor": "BIBS",
      "product_type": "Pacifier",
      "option_name": "Size",
      "option_values": [
        "1"
      ],
      "tags": [
        "BIBS",
        "Pacifier",
        "Ogólna"
      ],
      "files": {
        "https-b2b-aico2012-e-aico-com-pl-obrazki-bib000053-11103-20-458-20x-20458-jpg": "https://b2b:aico2012@e.aico.com.pl/Obrazki/BIB000053_11103%20(458%20x%20458).jpg"
      },
      "variants": [
        {
          "option_value": "1",
          "sku": "BIB000053",
          "barcode": "5713795243082",
          "price": "25.85",
          "detail_url": "https://e.aico.com.pl/ProduktySzczegoly.aspx?id_artykulu=3HySFqdpUDw9VEt2HAtoIw",
          "source_code": "11011103",
          "source_title": "BIBS 11011103 SMOCZEK LIBERTY PACIFIER KOLOR 2 PAK LATEX ROZMIAR 1 SZAŁWIA",
          "file_key": "https-b2b-aico2012-e-aico-com-pl-obrazki-bib000053-11103-20-458-20x-20458-jpg",
          "source_sku": "BIB000053"
        }
      ]
    },
    {
      "handle": "bibs-smoczek-studio-kolor-2-pak-latex-baby-blue-dusty-blue",
      "title": "BIBS Smoczek Studio Kolor 2 Pak Latex Baby Blue/Dusty Blue",
      "vendor": "BIBS",
      "product_type": "Pacifier",
      "option_name": "Size",
      "option_values": [
        "1"
      ],
      "tags": [
        "BIBS",
        "Pacifier",
        "Ogólna"
      ],
      "files": {
        "https-b2b-aico2012-e-aico-com-pl-obrazki-bib000044-5713795267590-2-bibs-studio-colour-pack-rnd-latex-block-babybluedustybluemix-2000x2000-20-600-20x-2060-jpg": "https://b2b:aico2012@e.aico.com.pl/Obrazki/BIB000044_5713795267590_2_BIBS_Studio_COLOUR_PACK_Rnd_Latex_Block_BabyBlueDustyBlueMix_2000x2000%20(600%20x%2060.jpg"
      },
      "variants": [
        {
          "option_value": "1",
          "sku": "BIB000044",
          "barcode": "5713795267590",
          "price": "23.92",
          "detail_url": "https://e.aico.com.pl/ProduktySzczegoly.aspx?id_artykulu=2Ylsw7XPyIaKK3ZFmBCnoQ",
          "source_code": "11022103",
          "source_title": "BIBS 11022103 SMOCZEK STUDIO KOLOR 2 PAK LATEX ROZMIAR 1 BABY BLUE/DUSTY BLUE",
          "file_key": "https-b2b-aico2012-e-aico-com-pl-obrazki-bib000044-5713795267590-2-bibs-studio-colour-pack-rnd-latex-block-babybluedustybluemix-2000x2000-20-600-20x-2060-jpg",
          "source_sku": "BIB000044"
        }
      ]
    },
    {
      "handle": "bibs-smoczek-studio-kolor-2-pak-latex-baby-pink-coral",
      "title": "BIBS Smoczek Studio Kolor 2 Pak Latex Baby Pink/Coral",
      "vendor": "BIBS",
      "product_type": "Pacifier",
      "option_name": "Size",
      "option_values": [
        "1"
      ],
      "tags": [
        "BIBS",
        "Pacifier",
        "Ogólna"
      ],
      "files": {
        "https-b2b-aico2012-e-aico-com-pl-obrazki-bib000043-5713795267583-2-bibs-studio-colour-pack-rnd-latex-s1-block-babypinkcoralmix-3-2000x2000-20-600-20x-206-jpg": "https://b2b:aico2012@e.aico.com.pl/Obrazki/BIB000043_5713795267583_2_BIBS_Studio_COLOUR_PACK_Rnd_Latex_S1_Block_BabyPinkCoralMix_3_2000x2000%20(600%20x%206.jpg"
      },
      "variants": [
        {
          "option_value": "1",
          "sku": "BIB000043",
          "barcode": "5713795267583",
          "price": "23.92",
          "detail_url": "https://e.aico.com.pl/ProduktySzczegoly.aspx?id_artykulu=F7wkBU-dbLT7Qon_uH2slQ",
          "source_code": "11022101",
          "source_title": "BIBS 11022101 SMOCZEK STUDIO KOLOR 2 PAK LATEX ROZMIAR 1 BABY PINK/CORAL",
          "file_key": "https-b2b-aico2012-e-aico-com-pl-obrazki-bib000043-5713795267583-2-bibs-studio-colour-pack-rnd-latex-s1-block-babypinkcoralmix-3-2000x2000-20-600-20x-206-jpg",
          "source_sku": "BIB000043"
        }
      ]
    },
    {
      "handle": "bibs-smoczek-studio-kolor-2-pak-latex-jasmin-roz",
      "title": "BIBS Smoczek Studio Kolor 2 Pak Latex Jaśmin/Róż",
      "vendor": "BIBS",
      "product_type": "Pacifier",
      "option_name": "Size",
      "option_values": [
        "1"
      ],
      "tags": [
        "BIBS",
        "Pacifier",
        "Ogólna"
      ],
      "files": {
        "https-b2b-aico2012-e-aico-com-pl-obrazki-bib000042-5713795259656-3-bibs-studio-colour-pack-rnd-latex-jasmine-blushmix-2000x2000-20-600-20x-20600-jpg": "https://b2b:aico2012@e.aico.com.pl/Obrazki/BIB000042_5713795259656_3_BIBS_Studio_COLOUR_PACK_Rnd_Latex_Jasmine_BlushMix_2000x2000%20(600%20x%20600).jpg"
      },
      "variants": [
        {
          "option_value": "1",
          "sku": "BIB000042",
          "barcode": "5713795259656",
          "price": "23.92",
          "detail_url": "https://e.aico.com.pl/ProduktySzczegoly.aspx?id_artykulu=4t2X-KRh-Mn6Lm4UJX4Rzg",
          "source_code": "11017103",
          "source_title": "BIBS 11017103 SMOCZEK STUDIO KOLOR 2 PAK LATEX ROZMIAR 1 JAŚMIN/RÓŻ",
          "file_key": "https-b2b-aico2012-e-aico-com-pl-obrazki-bib000042-5713795259656-3-bibs-studio-colour-pack-rnd-latex-jasmine-blushmix-2000x2000-20-600-20x-20600-jpg",
          "source_sku": "BIB000042"
        }
      ]
    },
    {
      "handle": "bibs-smoczek-studio-kolor-2-pak-latex-kosc-sloniowa-jasmin",
      "title": "BIBS Smoczek Studio Kolor 2 Pak Latex Kość Słoniowa/Jaśmin",
      "vendor": "BIBS",
      "product_type": "Pacifier",
      "option_name": "Size",
      "option_values": [
        "1"
      ],
      "tags": [
        "BIBS",
        "Pacifier",
        "Ogólna"
      ],
      "files": {
        "https-b2b-aico2012-e-aico-com-pl-obrazki-bib000041-5713795259656-3-bibs-studio-colour-pack-rnd-latex-jasmine-ivorymix-2000x2000-20-600-20x-20600-jpg": "https://b2b:aico2012@e.aico.com.pl/Obrazki/BIB000041_5713795259656_3_BIBS_Studio_COLOUR_PACK_Rnd_Latex_Jasmine_IvoryMix_2000x2000%20(600%20x%20600).jpg"
      },
      "variants": [
        {
          "option_value": "1",
          "sku": "BIB000041",
          "barcode": "5713795259670",
          "price": "23.92",
          "detail_url": "https://e.aico.com.pl/ProduktySzczegoly.aspx?id_artykulu=Fc-HGS-p-oIlreHIvYtDdg",
          "source_code": "11017101",
          "source_title": "BIBS 11017101 SMOCZEK STUDIO KOLOR 2 PAK LATEX ROZMIAR 1 KOŚĆ SŁONIOWA/JAŚMIN",
          "file_key": "https-b2b-aico2012-e-aico-com-pl-obrazki-bib000041-5713795259656-3-bibs-studio-colour-pack-rnd-latex-jasmine-ivorymix-2000x2000-20-600-20x-20600-jpg",
          "source_sku": "BIB000041"
        }
      ]
    },
    {
      "handle": "bibs-smoczek-studio-kolor-2-pak-latex-kosc-sloniowa-wanilia",
      "title": "BIBS Smoczek Studio Kolor 2 Pak Latex Kość Słoniowa/Wanilia",
      "vendor": "BIBS",
      "product_type": "Pacifier",
      "option_name": "Size",
      "option_values": [
        "1"
      ],
      "tags": [
        "BIBS",
        "Pacifier",
        "Ogólna"
      ],
      "files": {
        "https-b2b-aico2012-e-aico-com-pl-obrazki-bib000040-5713795259694-3-bibs-studio-colour-pack-rnd-latex-pin-ivoryvanillamix-2000x2000-20-600-20x-20600-jpg": "https://b2b:aico2012@e.aico.com.pl/Obrazki/BIB000040_5713795259694_3_BIBS_Studio_COLOUR_PACK_Rnd_Latex_Pin_IvoryVanillaMix_2000x2000%20(600%20x%20600).jpg"
      },
      "variants": [
        {
          "option_value": "1",
          "sku": "BIB000040",
          "barcode": "5713795259694",
          "price": "23.92",
          "detail_url": "https://e.aico.com.pl/ProduktySzczegoly.aspx?id_artykulu=pATwsrmC63NkEvGfcl6TIw",
          "source_code": "11015104",
          "source_title": "BIBS 11015104 SMOCZEK STUDIO KOLOR 2 PAK LATEX ROZMIAR 1 KOŚĆ SŁONIOWA/WANILIA",
          "file_key": "https-b2b-aico2012-e-aico-com-pl-obrazki-bib000040-5713795259694-3-bibs-studio-colour-pack-rnd-latex-pin-ivoryvanillamix-2000x2000-20-600-20x-20600-jpg",
          "source_sku": "BIB000040"
        }
      ]
    }
  ]
}